pytorch_scorch-0.0.7.dist-info/METADATA
pytorch_scorch-0.0.7.dist-info/RECORD
pytorch_scorch-0.0.7.dist-info/WHEEL
pytorch_scorch-0.0.7.dist-info/entry_points.txt
pytorch_scorch-0.0.7.dist-info/top_level.txt
scorch/__init__.py
scorch/train.py
scorch/trainer.py
scorch/transforms.py
scorch/utils.py
