Metadata-Version: 2.1
Name: pytorch-scorch
Version: 0.0.7
Summary: A set of scripts to make the Neural Network training with pytorch faster
Home-page: https://github.com/RomanovMikeV/scorch
Author: Mikhail Romanov
Author-email: romanov.michael.v@gmail.com
License: UNKNOWN
Platform: UNKNOWN
Classifier: Programming Language :: Python :: 3
Classifier: License :: OSI Approved :: MIT License
Classifier: Operating System :: OS Independent
